athenaeum/__init__.py
athenaeum/browser_automation.py
athenaeum/chrome_extension.py
athenaeum/datetime.py
athenaeum/db/__init__.py
athenaeum/db/engine.py
athenaeum/db/orm/__init__.py
athenaeum/db/orm/mongodb_orm.py
athenaeum/db/orm/mysql_orm.py
athenaeum/db/orm/postgresql_orm.py
athenaeum/db/orm/redis_orm.py
athenaeum/db/orm/sqlite_orm.py
athenaeum/decorators.py
athenaeum/entities.py
athenaeum/execute/__init__.py
athenaeum/execute/cmd.py
athenaeum/execute/js.py
athenaeum/file.py
athenaeum/image.py
athenaeum/logger.py
athenaeum/math.py
athenaeum/message_queue/__init__.py
athenaeum/message_queue/rabbitmq_message_queue.py
athenaeum/metas.py
athenaeum/network.py
athenaeum/notifier.py
athenaeum/process.py
athenaeum/project.py
athenaeum/render.py
athenaeum/scripts.py
athenaeum/task.py
athenaeum/templates/project/.env
athenaeum/templates/project/.gitignore
athenaeum/templates/project/config.py
athenaeum/templates/project/README.md.jinja2
athenaeum/templates/project/settings/settings.dev.toml
athenaeum/templates/project/settings/settings.prod.toml.jinja2
athenaeum/templates/project/settings/settings.toml
athenaeum/tools.py
athenaeum/url.py
athenaeum-0.1.8.dist-info/entry_points.txt
athenaeum-0.1.8.dist-info/LICENSE
athenaeum-0.1.8.dist-info/METADATA
athenaeum-0.1.8.dist-info/WHEEL
athenaeum-0.1.8.dist-info/RECORD
